ftransc/__init__.py
ftransc/constants.py
ftransc/errors.py
ftransc/launcher.py
ftransc/utils.py
ftransc/config/__init__.py
ftransc/config/config.py
ftransc/config/data/presets.json
ftransc/config/data/tagmap.json
ftransc/core/__init__.py
ftransc/core/transcoders.py
ftransc/core/queue/__init__.py
ftransc/core/queue/consumer.py
ftransc/metadata/__init__.py
ftransc/metadata/metadata.py
ftransc-7.0.3.dist-info/AUTHORS
ftransc-7.0.3.dist-info/LICENSE.txt
ftransc-7.0.3.dist-info/METADATA
ftransc-7.0.3.dist-info/WHEEL
ftransc-7.0.3.dist-info/entry_points.txt
ftransc-7.0.3.dist-info/top_level.txt
ftransc-7.0.3.dist-info/RECORD
