Metadata-Version: 2.1
Name: ftransc
Version: 7.0.3
Summary: ftransc is a python library for converting audio files across various formats.
Home-page: https://github.com/dopstar/ftransc
Author: Mkhanyisi Madlavana
Author-email: mkhanyisi@gmail.com
License: UNKNOWN
Download-URL: https://github.com/dopstar/ftransc/tarball/7.0.3
Keywords: Audio,Convert,ffmpeg,avconv,mp3
Platform: UNKNOWN
Classifier: Development Status :: 5 - Production/Stable
Classifier: Intended Audience :: End Users/Desktop
Classifier: Natural Language :: English
Classifier: Programming Language :: Python :: 3.6
Classifier: Programming Language :: Python :: 3.7
Classifier: Programming Language :: Python :: 3.8
Classifier: Programming Language :: Python :: 3.9
Requires-Dist: pafy
Requires-Dist: mutagen
Requires-Dist: plumbum
Requires-Dist: blessings
Requires-Dist: youtube-dl
